tarumba/__about__.py
tarumba/__init__.py
tarumba/__main__.py
tarumba/classifier.py
tarumba/cmd_parser.py
tarumba/config.py
tarumba/constants.py
tarumba/data_classes.py
tarumba/errors.py
tarumba/executor.py
tarumba/file_utils.py
tarumba/manager.py
tarumba/recompressor.py
tarumba/utils.py
tarumba/backend/__init__.py
tarumba/backend/ar.py
tarumba/backend/backend.py
tarumba/backend/bzip2.py
tarumba/backend/cpio.py
tarumba/backend/gzip.py
tarumba/backend/rar.py
tarumba/backend/tar.py
tarumba/backend/x7z.py
tarumba/backend/xz.py
tarumba/backend/zip.py
tarumba/gui/__init__.py
tarumba/gui/console.py
tarumba/gui/gui.py
tarumba/locale/es/LC_MESSAGES/tarumba.mo
tarumba/locale/es/LC_MESSAGES/tarumba.po
tarumba-0.0.8.dist-info/METADATA
tarumba-0.0.8.dist-info/WHEEL
tarumba-0.0.8.dist-info/entry_points.txt
tarumba-0.0.8.dist-info/licenses/COPYING
tarumba-0.0.8.dist-info/RECORD
