Metadata-Version: 2.4
Name: tarumba
Version: 0.0.8
Summary: The universal archive manager
Project-URL: Documentation, https://github.com/robertxgray/tarumba#readme
Project-URL: Issues, https://github.com/robertxgray/tarumba/issues
Project-URL: Source, https://github.com/robertxgray/tarumba
Author: Félix Medrano
License-Expression: GPL-3.0-or-later
License-File: COPYING
Classifier: Development Status :: 4 - Beta
Classifier: Programming Language :: Python
Classifier: Programming Language :: Python :: 3.8
Classifier: Programming Language :: Python :: 3.9
Classifier: Programming Language :: Python :: 3.10
Classifier: Programming Language :: Python :: 3.11
Classifier: Programming Language :: Python :: 3.12
Classifier: Programming Language :: Python :: 3.13
Classifier: Programming Language :: Python :: Implementation :: CPython
Classifier: Programming Language :: Python :: Implementation :: PyPy
Requires-Python: >=3.8
Requires-Dist: pexpect<5.0,>=4.0
Requires-Dist: python-magic<0.5.0,>=0.4.0
Requires-Dist: rich<14.0.0,>=13.0.0
Requires-Dist: typing-extensions<5.0.0,>=4.0.0
Requires-Dist: tzlocal<6.0,>=5.0
